gestvenv/__init__.py
gestvenv/__version__.py
gestvenv/_version.py
gestvenv/cli_main.py
gestvenv/ephemeral.py
gestvenv/backends/__init__.py
gestvenv/backends/backend_manager.py
gestvenv/backends/base.py
gestvenv/backends/pdm_backend.py
gestvenv/backends/pip_backend.py
gestvenv/backends/poetry_backend.py
gestvenv/backends/uv_backend.py
gestvenv/cli/__init__.py
gestvenv/cli/__main__.py
gestvenv/cli/commands/__init__.py
gestvenv/cli/commands/deps.py
gestvenv/cli/commands/diff.py
gestvenv/cli/commands/python_cmd.py
gestvenv/cli/commands/security.py
gestvenv/core/__init__.py
gestvenv/core/config_manager.py
gestvenv/core/env_manager.py
gestvenv/core/environment_manager.py
gestvenv/core/exceptions.py
gestvenv/core/models.py
gestvenv/core/package_manager.py
gestvenv/core/ephemeral/__init__.py
gestvenv/core/ephemeral/cgroups.py
gestvenv/core/ephemeral/cleanup.py
gestvenv/core/ephemeral/context.py
gestvenv/core/ephemeral/exceptions.py
gestvenv/core/ephemeral/lifecycle.py
gestvenv/core/ephemeral/manager.py
gestvenv/core/ephemeral/models.py
gestvenv/core/ephemeral/monitoring.py
gestvenv/core/ephemeral/storage.py
gestvenv/observability/__init__.py
gestvenv/observability/logging_config.py
gestvenv/observability/metrics.py
gestvenv/observability/tracing.py
gestvenv/python/__init__.py
gestvenv/python/downloader.py
gestvenv/python/manager.py
gestvenv/python/registry.py
gestvenv/services/__init__.py
gestvenv/services/async_cache_service.py
gestvenv/services/cache_service.py
gestvenv/services/diagnostic_service.py
gestvenv/services/migration_service.py
gestvenv/services/package_service.py
gestvenv/services/system_service.py
gestvenv/services/template_service.py
gestvenv/templates/__init__.py
gestvenv/templates/base_template.py
gestvenv/templates/default_config.json
gestvenv/templates/builtin/__init__.py
gestvenv/templates/builtin/basic.py
gestvenv/templates/builtin/cli.py
gestvenv/templates/builtin/data_science.py
gestvenv/templates/builtin/django.py
gestvenv-2.0.3.dist-info/licenses/LICENSE
gestvenv-2.0.3.dist-info/METADATA
gestvenv-2.0.3.dist-info/WHEEL
gestvenv-2.0.3.dist-info/entry_points.txt
gestvenv-2.0.3.dist-info/top_level.txt
gestvenv-2.0.3.dist-info/RECORD
