Metadata-Version: 2.4
Name: gestvenv
Version: 2.0.3
Summary: Gestionnaire d'environnements virtuels Python moderne
Author-email: GestVenv Team <contact@gestvenv.dev>
License-Expression: MIT
Project-URL: Homepage, https://github.com/gestvenv/gestvenv
Project-URL: Documentation, https://gestvenv.readthedocs.io
Project-URL: Repository, https://github.com/gestvenv/gestvenv.git
Project-URL: Changelog, https://github.com/gestvenv/gestvenv/blob/main/CHANGELOG.md
Project-URL: Issues, https://github.com/gestvenv/gestvenv/issues
Keywords: python,virtualenv,package-manager,environment,pyproject
Classifier: Development Status :: 5 - Production/Stable
Classifier: Intended Audience :: Developers
Classifier: Operating System :: OS Independent
Classifier: Programming Language :: Python :: 3
Classifier: Programming Language :: Python :: 3.9
Classifier: Programming Language :: Python :: 3.10
Classifier: Programming Language :: Python :: 3.11
Classifier: Programming Language :: Python :: 3.12
Classifier: Programming Language :: Python :: 3.13
Classifier: Topic :: Software Development :: Libraries :: Python Modules
Classifier: Topic :: System :: Software Distribution
Classifier: Topic :: Software Development :: Build Tools
Requires-Python: >=3.9
License-File: LICENSE
Requires-Dist: packaging>=21.0
Requires-Dist: tomli>=2.0.0; python_version < "3.11"
Requires-Dist: tomlkit>=0.11.0
Requires-Dist: click>=8.0.0
Requires-Dist: rich>=13.0.0
Requires-Dist: psutil>=5.9.0
Provides-Extra: dev
Requires-Dist: pytest>=7.0; extra == "dev"
Requires-Dist: pytest-cov>=4.0; extra == "dev"
Requires-Dist: pytest-mock>=3.6; extra == "dev"
Requires-Dist: pytest-asyncio>=0.21; extra == "dev"
Requires-Dist: black>=23.0; extra == "dev"
Requires-Dist: isort>=5.10; extra == "dev"
Requires-Dist: mypy>=1.0; extra == "dev"
Requires-Dist: flake8>=6.0; extra == "dev"
Requires-Dist: pre-commit>=3.0; extra == "dev"
Provides-Extra: docs
Requires-Dist: sphinx>=6.0; extra == "docs"
Requires-Dist: sphinx-rtd-theme>=1.0; extra == "docs"
Requires-Dist: myst-parser>=1.0; extra == "docs"
Requires-Dist: sphinx-click>=4.0; extra == "docs"
Provides-Extra: performance
Requires-Dist: uv>=0.1.0; extra == "performance"
Provides-Extra: full
Requires-Dist: uv>=0.1.0; extra == "full"
Requires-Dist: tomli-w>=1.0.0; extra == "full"
Requires-Dist: psutil>=5.9.0; extra == "full"
Provides-Extra: test
Requires-Dist: pytest>=7.0; extra == "test"
Requires-Dist: pytest-cov>=4.0; extra == "test"
Requires-Dist: pytest-mock>=3.6; extra == "test"
Requires-Dist: pytest-asyncio>=0.21; extra == "test"
Requires-Dist: psutil>=5.9.0; extra == "test"
Dynamic: license-file
